log.py
gpuprog_log-1.1.2.dist-info/METADATA
gpuprog_log-1.1.2.dist-info/WHEEL
gpuprog_log-1.1.2.dist-info/top_level.txt
gpuprog_log-1.1.2.dist-info/RECORD
