Metadata-Version: 2.1
Name: gpuprog-log
Version: 1.1.2
Summary: Logging for microservices
Author-email: gpuprog <gpuprog@gmail.com>
Project-URL: Homepage, https://github.com/gpuprog/log#readme
Project-URL: Issues, https://github.com/gpuprog/log/issues
Classifier: Programming Language :: Python :: 3
Classifier: License :: OSI Approved :: MIT License
Classifier: Operating System :: OS Independent
Requires-Python: >=3.8
Requires-Dist: aiofile
Requires-Dist: aiohttp
Requires-Dist: aiosmtplib
Requires-Dist: ujson
